[
    {
        "ChannelName": "processed",
        "DataSource": {
            "S3DataSource": {
                "S3DataType": "S3Prefix",
                "S3DataDistributionType": "FullyReplicated",
                "S3Uri": "s3://S3_BUCKET/input/processed"
            }
        },
        "ContentType": "text/csv",
        "CompressionType": "None"
    },
    {
        "ChannelName": "external",
        "DataSource": {
            "S3DataSource": {
                "S3DataType": "S3Prefix",
                "S3DataDistributionType": "FullyReplicated",
                "S3Uri": "s3://S3_BUCKET/input/external"
            }
        },
        "ContentType": "text/csv",
        "CompressionType": "None"
    },
    {
        "ChannelName": "test",
        "DataSource": {
            "S3DataSource": {
                "S3DataType": "S3Prefix",
                "S3DataDistributionType": "FullyReplicated",
                "S3Uri": "s3://S3_BUCKET/input/test"
            }
        },
        "ContentType": "text/csv",
        "CompressionType": "None"
    }
]
